alora/__init__.py
alora/_version.py
alora/config.py
alora/layer.py
alora/model.py
alora/multi_collator.py
alora/peft_model_alora.py
alora/tokenize_alora.py
alora-0.3.0.dist-info/licenses/LICENSE
alora-0.3.0.dist-info/METADATA
alora-0.3.0.dist-info/WHEEL
alora-0.3.0.dist-info/top_level.txt
alora-0.3.0.dist-info/RECORD
