Metadata-Version: 2.4
Name: alora
Version: 0.3.0
Summary: Activated LoRA (aLoRA) is a low rank adapter architecture that allows for reusing existing base model KV cache.
Author-email: Kristjan Greenewald <kristjan.h.greenewald@ibm.com>
License: MIT License
Project-URL: Homepage, https://github.com/IBM/activated-lora
Project-URL: Repository, https://github.com/IBM/activated-lora
Keywords: activated-lora,lora,alora
Classifier: License :: OSI Approved :: MIT License
Classifier: Development Status :: 3 - Alpha
Classifier: Programming Language :: Python :: 3
Classifier: Programming Language :: Python :: 3.9
Classifier: Programming Language :: Python :: 3.10
Classifier: Programming Language :: Python :: 3.11
Classifier: Programming Language :: Python :: 3.12
Requires-Python: ~=3.9
License-File: LICENSE
Requires-Dist: click
Requires-Dist: peft>=0.14
Requires-Dist: transformers
Dynamic: license-file
